basicbedrock/__init__.py
basicbedrock/basicbedrock.py
basicbedrock/guardrails.py
basicbedrock/guardrails_baseclasses.py
basicbedrock/models/__init__.py
basicbedrock/models/ai21.py
basicbedrock/models/amazon.py
basicbedrock/models/anthropic.py
basicbedrock/models/baseclasses.py
basicbedrock/models/cohere.py
basicbedrock/models/meta.py
basicbedrock/models/mistral.py
basicbedrock-0.2.4.dist-info/LICENSE
basicbedrock-0.2.4.dist-info/METADATA
basicbedrock-0.2.4.dist-info/WHEEL
basicbedrock-0.2.4.dist-info/top_level.txt
basicbedrock-0.2.4.dist-info/RECORD
