Metadata-Version: 2.1
Name: basicbedrock
Version: 0.2.4
Summary: An abstraction layer for AWS Bedrock.  Removes the need to keep track of response/request schemas.
Author-email: cyberitech <mattsod@kaizencyber.io>
Maintainer-email: cyberitech <mattsod@kaizencyber.io>
License: Copyright 2024 
Project-URL: Homepage, https://github.com/cyberitech/BasicBedrock
Project-URL: Issues, https://github.com/cyberitech/BasicBedrock/issues
Classifier: Development Status :: 4 - Beta
Classifier: License :: OSI Approved :: MIT License
Classifier: Operating System :: OS Independent
Classifier: Natural Language :: English
Classifier: Programming Language :: Python :: 3.8
Requires-Python: >=3.8
License-File: LICENSE
Requires-Dist: boto3 >=1.34.94
Requires-Dist: pydantic >=2.6.0
